[{"timestamp":"2024-05-31T01:14:33.394Z","count":0,"uniques":0},{"timestamp":"2024-06-01T01:18:18.460Z","count":0,"uniques":0},{"timestamp":"2024-06-02T01:18:26.134Z","count":0,"uniques":0},{"timestamp":"2024-06-03T01:15:08.157Z","count":0,"uniques":0},{"timestamp":"2024-06-04T01:14:52.053Z","count":0,"uniques":0},{"timestamp":"2024-06-05T01:14:15.873Z","count":0,"uniques":0},{"timestamp":"2024-06-06T01:14:19.492Z","count":0,"uniques":0},{"timestamp":"2024-06-07T01:16:45.374Z","count":0,"uniques":0},{"timestamp":"2024-06-08T01:14:40.873Z","count":0,"uniques":0},{"timestamp":"2024-06-09T01:21:00.624Z","count":0,"uniques":0},{"timestamp":"2024-06-10T01:17:03.027Z","count":0,"uniques":0},{"timestamp":"2024-06-11T01:15:53.251Z","count":0,"uniques":0},{"timestamp":"2024-06-12T01:15:43.240Z","count":0,"uniques":0},{"timestamp":"2024-06-13T01:15:25.624Z","count":0,"uniques":0},{"timestamp":"2024-06-14T01:15:06.126Z","count":0,"uniques":0},{"timestamp":"2024-06-15T01:15:04.258Z","count":0,"uniques":0},{"timestamp":"2024-06-16T01:20:54.207Z","count":0,"uniques":0},{"timestamp":"2024-06-17T01:17:49.287Z","count":0,"uniques":0},{"timestamp":"2024-06-18T01:15:53.789Z","count":0,"uniques":0},{"timestamp":"2024-06-19T01:16:07.643Z","count":0,"uniques":0},{"timestamp":"2024-06-20T01:14:16.315Z","count":0,"uniques":0},{"timestamp":"2024-06-21T01:14:48.749Z","count":0,"uniques":0},{"timestamp":"2024-06-22T01:14:11.654Z","count":0,"uniques":0},{"timestamp":"2024-06-23T01:20:03.974Z","count":0,"uniques":0},{"timestamp":"2024-06-24T01:16:58.452Z","count":0,"uniques":0},{"timestamp":"2024-06-25T01:15:47.811Z","count":0,"uniques":0},{"timestamp":"2024-06-26T01:15:43.413Z","count":0,"uniques":0},{"timestamp":"2024-06-27T01:16:03.786Z","count":0,"uniques":0},{"timestamp":"2024-06-28T01:16:07.700Z","count":0,"uniques":0},{"timestamp":"2024-06-29T01:14:43.859Z","count":0,"uniques":0},{"timestamp":"2024-06-30T01:22:08.609Z","count":0,"uniques":0},{"timestamp":"2024-07-01T01:23:52.542Z","count":0,"uniques":0},{"timestamp":"2024-07-02T01:16:30.911Z","count":0,"uniques":0},{"timestamp":"2024-07-03T01:16:08.068Z","count":0,"uniques":0},{"timestamp":"2024-07-04T01:16:31.101Z","count":0,"uniques":0},{"timestamp":"2024-07-05T01:16:30.662Z","count":0,"uniques":0},{"timestamp":"2024-07-06T01:14:31.159Z","count":0,"uniques":0},{"timestamp":"2024-07-07T01:22:43.724Z","count":0,"uniques":0},{"timestamp":"2024-07-08T01:18:24.396Z","count":0,"uniques":0},{"timestamp":"2024-07-09T01:17:37.157Z","count":0,"uniques":0},{"timestamp":"2024-07-10T01:18:03.050Z","count":0,"uniques":0},{"timestamp":"2024-07-11T01:18:17.639Z","count":0,"uniques":0},{"timestamp":"2024-07-12T01:17:01.315Z","count":0,"uniques":0},{"timestamp":"2024-07-13T01:17:54.894Z","count":0,"uniques":0},{"timestamp":"2024-07-14T01:23:39.836Z","count":0,"uniques":0},{"timestamp":"2024-07-15T01:19:55.368Z","count":0,"uniques":0},{"timestamp":"2024-07-16T01:19:26.355Z","count":0,"uniques":0},{"timestamp":"2024-07-17T01:18:23.700Z","count":0,"uniques":0},{"timestamp":"2024-07-18T01:16:57.313Z","count":0,"uniques":0},{"timestamp":"2024-07-19T01:17:46.442Z","count":0,"uniques":0},{"timestamp":"2024-07-20T01:16:35.299Z","count":0,"uniques":0},{"timestamp":"2024-07-21T01:23:41.814Z","count":0,"uniques":0},{"timestamp":"2024-07-22T01:20:41.699Z","count":0,"uniques":0},{"timestamp":"2024-07-23T01:18:42.894Z","count":0,"uniques":0},{"timestamp":"2024-07-24T01:18:51.835Z","count":0,"uniques":0},{"timestamp":"2024-07-25T01:18:21.689Z","count":0,"uniques":0},{"timestamp":"2024-07-26T01:17:52.016Z","count":0,"uniques":0},{"timestamp":"2024-07-27T01:17:14.736Z","count":0,"uniques":0},{"timestamp":"2024-07-28T01:24:18.808Z","count":0,"uniques":0},{"timestamp":"2024-07-29T01:20:23.296Z","count":0,"uniques":0},{"timestamp":"2024-07-30T01:18:47.538Z","count":0,"uniques":0},{"timestamp":"2024-07-31T01:05:47.508Z","count":0,"uniques":0},{"timestamp":"2024-08-01T01:25:08.675Z","count":0,"uniques":0},{"timestamp":"2024-08-02T01:18:27.629Z","count":0,"uniques":0},{"timestamp":"2024-08-03T01:17:36.661Z","count":0,"uniques":0},{"timestamp":"2024-08-04T01:24:28.064Z","count":0,"uniques":0},{"timestamp":"2024-08-05T01:20:37.122Z","count":0,"uniques":0},{"timestamp":"2024-08-06T01:19:15.796Z","count":0,"uniques":0},{"timestamp":"2024-08-07T01:20:07.163Z","count":0,"uniques":0},{"timestamp":"2024-08-08T01:19:47.109Z","count":0,"uniques":0},{"timestamp":"2024-08-09T01:20:32.206Z","count":0,"uniques":0},{"timestamp":"2024-08-10T01:20:16.067Z","count":0,"uniques":0},{"timestamp":"2024-08-11T01:25:40.039Z","count":0,"uniques":0},{"timestamp":"2024-08-12T01:21:45.663Z","count":0,"uniques":0},{"timestamp":"2024-08-13T01:21:39.030Z","count":0,"uniques":0},{"timestamp":"2024-08-14T01:20:19.864Z","count":0,"uniques":0},{"timestamp":"2024-08-15T01:16:05.624Z","count":0,"uniques":0},{"timestamp":"2024-08-16T01:19:40.865Z","count":0,"uniques":0},{"timestamp":"2024-08-17T01:17:25.040Z","count":0,"uniques":0},{"timestamp":"2024-08-18T01:24:30.442Z","count":0,"uniques":0},{"timestamp":"2024-08-19T00:00:00.000Z","count":3,"uniques":1},{"timestamp":"2024-08-20T01:19:21.599Z","count":0,"uniques":0},{"timestamp":"2024-08-21T01:19:44.078Z","count":0,"uniques":0},{"timestamp":"2024-08-22T01:21:30.405Z","count":0,"uniques":0},{"timestamp":"2024-08-23T01:20:11.962Z","count":0,"uniques":0},{"timestamp":"2024-08-24T01:18:39.671Z","count":0,"uniques":0},{"timestamp":"2024-08-25T01:26:45.736Z","count":0,"uniques":0},{"timestamp":"2024-08-26T01:21:10.761Z","count":0,"uniques":0},{"timestamp":"2024-08-27T01:21:46.565Z","count":0,"uniques":0},{"timestamp":"2024-08-28T01:22:33.934Z","count":0,"uniques":0},{"timestamp":"2024-08-29T01:22:50.229Z","count":0,"uniques":0},{"timestamp":"2024-08-30T01:23:21.706Z","count":0,"uniques":0},{"timestamp":"2024-08-31T01:22:49.704Z","count":0,"uniques":0},{"timestamp":"2024-09-01T01:42:18.499Z","count":0,"uniques":0},{"timestamp":"2024-09-02T01:24:58.983Z","count":0,"uniques":0},{"timestamp":"2024-09-03T01:22:26.506Z","count":0,"uniques":0},{"timestamp":"2024-09-04T01:23:54.288Z","count":0,"uniques":0},{"timestamp":"2024-09-05T01:23:52.395Z","count":0,"uniques":0},{"timestamp":"2024-09-06T01:23:40.301Z","count":0,"uniques":0},{"timestamp":"2024-09-07T01:22:22.815Z","count":0,"uniques":0},{"timestamp":"2024-09-08T01:36:26.966Z","count":0,"uniques":0},{"timestamp":"2024-09-09T01:26:20.619Z","count":0,"uniques":0},{"timestamp":"2024-09-10T06:27:27.436Z","count":0,"uniques":0},{"timestamp":"2024-09-11T01:23:57.258Z","count":0,"uniques":0},{"timestamp":"2024-09-12T01:24:14.101Z","count":0,"uniques":0},{"timestamp":"2024-09-13T01:24:49.618Z","count":0,"uniques":0},{"timestamp":"2024-09-14T01:23:23.989Z","count":0,"uniques":0},{"timestamp":"2024-09-15T01:39:50.456Z","count":0,"uniques":0},{"timestamp":"2024-09-16T01:36:53.861Z","count":0,"uniques":0},{"timestamp":"2024-09-17T01:11:06.236Z","count":0,"uniques":0},{"timestamp":"2024-09-18T01:24:26.027Z","count":0,"uniques":0},{"timestamp":"2024-09-19T01:26:05.864Z","count":0,"uniques":0},{"timestamp":"2024-09-20T01:26:18.050Z","count":0,"uniques":0},{"timestamp":"2024-09-21T01:24:34.079Z","count":0,"uniques":0},{"timestamp":"2024-09-22T01:40:07.557Z","count":0,"uniques":0},{"timestamp":"2024-09-23T01:28:01.451Z","count":0,"uniques":0},{"timestamp":"2024-09-24T01:28:23.575Z","count":0,"uniques":0},{"timestamp":"2024-09-25T01:36:37.749Z","count":0,"uniques":0},{"timestamp":"2024-09-26T01:27:29.168Z","count":0,"uniques":0},{"timestamp":"2024-09-27T01:28:09.210Z","count":0,"uniques":0},{"timestamp":"2024-09-28T01:27:28.356Z","count":0,"uniques":0},{"timestamp":"2024-09-29T01:41:39.683Z","count":0,"uniques":0},{"timestamp":"2024-09-30T01:38:26.526Z","count":0,"uniques":0},{"timestamp":"2024-10-01T01:43:39.252Z","count":0,"uniques":0},{"timestamp":"2024-10-02T01:27:58.690Z","count":0,"uniques":0},{"timestamp":"2024-10-03T01:28:21.134Z","count":0,"uniques":0},{"timestamp":"2024-10-04T01:28:40.908Z","count":0,"uniques":0},{"timestamp":"2024-10-05T01:27:05.530Z","count":0,"uniques":0},{"timestamp":"2024-10-06T01:41:12.964Z","count":0,"uniques":0},{"timestamp":"2024-10-07T01:38:23.600Z","count":0,"uniques":0},{"timestamp":"2024-10-08T01:35:49.255Z","count":0,"uniques":0},{"timestamp":"2024-10-09T01:27:31.672Z","count":0,"uniques":0},{"timestamp":"2024-10-10T01:27:52.007Z","count":0,"uniques":0},{"timestamp":"2024-10-11T01:27:51.141Z","count":0,"uniques":0},{"timestamp":"2024-10-12T01:26:13.567Z","count":0,"uniques":0},{"timestamp":"2024-10-13T01:40:46.694Z","count":0,"uniques":0},{"timestamp":"2024-10-14T01:38:01.549Z","count":0,"uniques":0},{"timestamp":"2024-10-15T01:37:00.686Z","count":0,"uniques":0},{"timestamp":"2024-10-16T01:37:19.735Z","count":0,"uniques":0},{"timestamp":"2024-10-17T01:36:05.592Z","count":0,"uniques":0},{"timestamp":"2024-10-18T01:36:16.086Z","count":0,"uniques":0},{"timestamp":"2024-10-19T01:27:27.165Z","count":0,"uniques":0},{"timestamp":"2024-10-20T01:42:43.077Z","count":0,"uniques":0},{"timestamp":"2024-10-21T01:38:32.558Z","count":0,"uniques":0},{"timestamp":"2024-10-22T01:37:16.063Z","count":0,"uniques":0},{"timestamp":"2024-10-23T01:28:03.581Z","count":0,"uniques":0},{"timestamp":"2024-10-24T01:28:22.852Z","count":0,"uniques":0},{"timestamp":"2024-10-25T01:36:38.441Z","count":0,"uniques":0},{"timestamp":"2024-10-26T01:26:10.940Z","count":0,"uniques":0},{"timestamp":"2024-10-27T01:41:38.611Z","count":0,"uniques":0},{"timestamp":"2024-10-28T01:39:59.098Z","count":0,"uniques":0},{"timestamp":"2024-10-29T01:38:18.177Z","count":0,"uniques":0},{"timestamp":"2024-10-30T01:37:05.809Z","count":0,"uniques":0},{"timestamp":"2024-10-31T01:37:56.908Z","count":0,"uniques":0},{"timestamp":"2024-11-01T01:43:17.473Z","count":0,"uniques":0},{"timestamp":"2024-11-02T01:27:23.145Z","count":0,"uniques":0},{"timestamp":"2024-11-03T01:41:40.666Z","count":0,"uniques":0},{"timestamp":"2024-11-04T01:38:30.855Z","count":0,"uniques":0},{"timestamp":"2024-11-05T01:27:12.994Z","count":0,"uniques":0},{"timestamp":"2024-11-06T01:26:33.714Z","count":0,"uniques":0},{"timestamp":"2024-11-07T01:27:18.655Z","count":0,"uniques":0},{"timestamp":"2024-11-08T01:27:10.396Z","count":0,"uniques":0},{"timestamp":"2024-11-09T01:25:00.948Z","count":0,"uniques":0},{"timestamp":"2024-11-10T01:39:17.121Z","count":0,"uniques":0},{"timestamp":"2024-11-11T01:36:18.296Z","count":0,"uniques":0},{"timestamp":"2024-11-12T01:26:25.211Z","count":0,"uniques":0},{"timestamp":"2024-11-13T01:28:02.453Z","count":0,"uniques":0},{"timestamp":"2024-11-14T01:28:01.453Z","count":0,"uniques":0},{"timestamp":"2024-11-15T01:41:10.348Z","count":0,"uniques":0},{"timestamp":"2024-11-16T01:39:02.213Z","count":0,"uniques":0},{"timestamp":"2024-11-17T01:44:56.919Z","count":0,"uniques":0},{"timestamp":"2024-11-18T01:43:08.610Z","count":0,"uniques":0},{"timestamp":"2024-11-19T01:41:05.041Z","count":0,"uniques":0},{"timestamp":"2024-11-20T01:39:59.600Z","count":0,"uniques":0},{"timestamp":"2024-11-21T01:40:02.671Z","count":0,"uniques":0},{"timestamp":"2024-11-22T01:41:13.038Z","count":0,"uniques":0},{"timestamp":"2024-11-23T01:38:23.233Z","count":0,"uniques":0},{"timestamp":"2024-11-24T01:45:30.539Z","count":0,"uniques":0},{"timestamp":"2024-11-25T01:42:49.133Z","count":0,"uniques":0},{"timestamp":"2024-11-26T01:41:40.706Z","count":0,"uniques":0},{"timestamp":"2024-11-27T01:42:59.681Z","count":0,"uniques":0},{"timestamp":"2024-11-28T01:42:41.699Z","count":0,"uniques":0},{"timestamp":"2024-11-29T01:42:53.243Z","count":0,"uniques":0},{"timestamp":"2024-11-30T01:40:03.110Z","count":0,"uniques":0},{"timestamp":"2024-12-01T01:56:55.725Z","count":0,"uniques":0},{"timestamp":"2024-12-02T01:46:21.456Z","count":0,"uniques":0},{"timestamp":"2024-12-03T01:44:35.414Z","count":0,"uniques":0},{"timestamp":"2024-12-04T01:45:06.187Z","count":0,"uniques":0},{"timestamp":"2024-12-05T01:44:49.293Z","count":0,"uniques":0},{"timestamp":"2024-12-06T01:43:50.058Z","count":0,"uniques":0},{"timestamp":"2024-12-07T01:43:01.384Z","count":0,"uniques":0},{"timestamp":"2024-12-08T01:50:45.573Z","count":0,"uniques":0},{"timestamp":"2024-12-09T01:47:44.353Z","count":0,"uniques":0},{"timestamp":"2024-12-10T01:46:09.778Z","count":0,"uniques":0},{"timestamp":"2024-12-11T01:44:49.572Z","count":0,"uniques":0},{"timestamp":"2024-12-12T01:44:20.294Z","count":0,"uniques":0},{"timestamp":"2024-12-13T01:46:00.351Z","count":0,"uniques":0},{"timestamp":"2024-12-14T01:41:17.985Z","count":0,"uniques":0},{"timestamp":"2024-12-15T01:50:42.769Z","count":0,"uniques":0},{"timestamp":"2024-12-16T01:47:48.390Z","count":0,"uniques":0},{"timestamp":"2024-12-17T01:44:19.040Z","count":0,"uniques":0},{"timestamp":"2024-12-18T01:41:11.486Z","count":0,"uniques":0},{"timestamp":"2024-12-19T01:41:31.158Z","count":0,"uniques":0},{"timestamp":"2024-12-20T01:36:51.850Z","count":0,"uniques":0},{"timestamp":"2024-12-21T01:27:28.957Z","count":0,"uniques":0},{"timestamp":"2024-12-22T01:42:32.740Z","count":0,"uniques":0},{"timestamp":"2024-12-23T01:38:00.139Z","count":0,"uniques":0},{"timestamp":"2024-12-24T01:35:48.289Z","count":0,"uniques":0},{"timestamp":"2024-12-25T01:27:47.183Z","count":0,"uniques":0},{"timestamp":"2024-12-26T01:27:54.788Z","count":0,"uniques":0},{"timestamp":"2024-12-27T01:28:26.956Z","count":0,"uniques":0},{"timestamp":"2024-12-28T01:27:01.428Z","count":0,"uniques":0},{"timestamp":"2024-12-29T01:43:03.428Z","count":0,"uniques":0},{"timestamp":"2024-12-30T01:38:37.571Z","count":0,"uniques":0},{"timestamp":"2024-12-31T01:28:16.155Z","count":0,"uniques":0},{"timestamp":"2025-01-01T01:43:12.735Z","count":0,"uniques":0},{"timestamp":"2025-01-02T01:28:05.241Z","count":0,"uniques":0},{"timestamp":"2025-01-03T01:36:09.481Z","count":0,"uniques":0},{"timestamp":"2025-01-04T01:27:18.055Z","count":0,"uniques":0},{"timestamp":"2025-01-05T01:42:19.576Z","count":0,"uniques":0},{"timestamp":"2025-01-06T01:40:15.967Z","count":0,"uniques":0},{"timestamp":"2025-01-07T01:36:59.430Z","count":0,"uniques":0},{"timestamp":"2025-01-08T01:36:36.863Z","count":0,"uniques":0},{"timestamp":"2025-01-09T02:09:24.033Z","count":0,"uniques":0},{"timestamp":"2025-01-10T01:38:36.087Z","count":0,"uniques":0},{"timestamp":"2025-01-11T01:36:17.113Z","count":0,"uniques":0},{"timestamp":"2025-01-12T01:43:55.808Z","count":0,"uniques":0},{"timestamp":"2025-01-13T01:40:53.450Z","count":0,"uniques":0},{"timestamp":"2025-01-14T01:25:12.807Z","count":0,"uniques":0},{"timestamp":"2025-01-15T01:26:58.932Z","count":0,"uniques":0},{"timestamp":"2025-01-16T01:26:21.616Z","count":0,"uniques":0},{"timestamp":"2025-01-17T01:25:43.206Z","count":0,"uniques":0},{"timestamp":"2025-01-18T01:23:55.361Z","count":0,"uniques":0},{"timestamp":"2025-01-19T01:39:25.328Z","count":0,"uniques":0},{"timestamp":"2025-01-20T01:27:29.910Z","count":0,"uniques":0},{"timestamp":"2025-01-21T01:26:09.687Z","count":0,"uniques":0},{"timestamp":"2025-01-22T01:28:03.663Z","count":0,"uniques":0},{"timestamp":"2025-01-23T01:26:23.490Z","count":0,"uniques":0},{"timestamp":"2025-01-24T01:26:50.792Z","count":0,"uniques":0},{"timestamp":"2025-01-25T01:22:47.461Z","count":0,"uniques":0},{"timestamp":"2025-01-26T01:36:09.867Z","count":0,"uniques":0},{"timestamp":"2025-01-27T01:27:41.543Z","count":0,"uniques":0},{"timestamp":"2025-01-28T01:26:23.954Z","count":0,"uniques":0},{"timestamp":"2025-01-29T01:26:17.128Z","count":0,"uniques":0},{"timestamp":"2025-01-30T01:25:16.981Z","count":0,"uniques":0},{"timestamp":"2025-01-31T01:27:01.290Z","count":0,"uniques":0},{"timestamp":"2025-02-01T01:38:26.783Z","count":0,"uniques":0},{"timestamp":"2025-02-02T01:37:34.245Z","count":0,"uniques":0},{"timestamp":"2025-02-03T01:27:40.302Z","count":0,"uniques":0},{"timestamp":"2025-02-04T01:26:40.937Z","count":0,"uniques":0},{"timestamp":"2025-02-05T01:27:52.211Z","count":0,"uniques":0},{"timestamp":"2025-02-06T01:28:07.089Z","count":0,"uniques":0},{"timestamp":"2025-02-07T01:28:12.598Z","count":0,"uniques":0},{"timestamp":"2025-02-08T01:25:35.752Z","count":0,"uniques":0},{"timestamp":"2025-02-09T01:38:58.867Z","count":0,"uniques":0},{"timestamp":"2025-02-10T01:36:41.145Z","count":0,"uniques":0},{"timestamp":"2025-02-11T01:27:52.124Z","count":0,"uniques":0},{"timestamp":"2025-02-12T01:27:58.733Z","count":0,"uniques":0},{"timestamp":"2025-02-13T01:36:03.725Z","count":0,"uniques":0},{"timestamp":"2025-02-14T01:28:03.102Z","count":0,"uniques":0},{"timestamp":"2025-02-15T01:27:24.033Z","count":0,"uniques":0},{"timestamp":"2025-02-16T01:42:03.661Z","count":0,"uniques":0},{"timestamp":"2025-02-17T01:38:56.205Z","count":0,"uniques":0},{"timestamp":"2025-02-18T01:28:04.303Z","count":0,"uniques":0},{"timestamp":"2025-02-19T01:36:35.376Z","count":0,"uniques":0},{"timestamp":"2025-02-20T01:37:08.388Z","count":0,"uniques":0},{"timestamp":"2025-02-21T01:37:25.608Z","count":0,"uniques":0},{"timestamp":"2025-02-22T01:26:46.417Z","count":0,"uniques":0},{"timestamp":"2025-02-23T01:41:55.800Z","count":0,"uniques":0},{"timestamp":"2025-02-24T01:39:33.241Z","count":0,"uniques":0},{"timestamp":"2025-02-25T01:38:49.798Z","count":0,"uniques":0},{"timestamp":"2025-02-26T01:38:23.530Z","count":0,"uniques":0},{"timestamp":"2025-02-27T01:38:51.355Z","count":0,"uniques":0},{"timestamp":"2025-02-28T01:39:00.184Z","count":0,"uniques":0},{"timestamp":"2025-03-01T01:44:01.013Z","count":0,"uniques":0},{"timestamp":"2025-03-02T01:43:07.935Z","count":0,"uniques":0},{"timestamp":"2025-03-03T01:41:27.476Z","count":0,"uniques":0},{"timestamp":"2025-03-04T01:40:14.066Z","count":0,"uniques":0},{"timestamp":"2025-03-05T01:39:56.676Z","count":0,"uniques":0},{"timestamp":"2025-03-06T01:40:29.286Z","count":0,"uniques":0},{"timestamp":"2025-03-07T01:40:55.184Z","count":0,"uniques":0},{"timestamp":"2025-03-08T01:14:39.123Z","count":0,"uniques":0},{"timestamp":"2025-03-09T01:20:31.459Z","count":0,"uniques":0},{"timestamp":"2025-03-10T01:18:26.167Z","count":0,"uniques":0},{"timestamp":"2025-03-11T01:40:57.361Z","count":0,"uniques":0},{"timestamp":"2025-03-12T01:40:18.117Z","count":0,"uniques":0},{"timestamp":"2025-03-13T01:41:42.523Z","count":0,"uniques":0},{"timestamp":"2025-03-14T01:39:41.410Z","count":0,"uniques":0},{"timestamp":"2025-03-15T01:39:19.459Z","count":0,"uniques":0},{"timestamp":"2025-03-16T01:46:44.796Z","count":0,"uniques":0},{"timestamp":"2025-03-17T01:43:59.609Z","count":0,"uniques":0},{"timestamp":"2025-03-18T01:41:58.516Z","count":0,"uniques":0},{"timestamp":"2025-03-19T01:42:24.768Z","count":0,"uniques":0},{"timestamp":"2025-03-20T01:41:09.978Z","count":0,"uniques":0},{"timestamp":"2025-03-21T01:42:44.845Z","count":0,"uniques":0},{"timestamp":"2025-03-22T01:40:34.978Z","count":0,"uniques":0},{"timestamp":"2025-03-23T01:47:48.848Z","count":0,"uniques":0},{"timestamp":"2025-03-24T01:45:45.498Z","count":0,"uniques":0},{"timestamp":"2025-03-25T01:43:30.578Z","count":0,"uniques":0},{"timestamp":"2025-03-26T01:42:54.547Z","count":0,"uniques":0},{"timestamp":"2025-03-27T01:42:37.651Z","count":0,"uniques":0},{"timestamp":"2025-03-28T01:42:47.482Z","count":0,"uniques":0},{"timestamp":"2025-03-29T01:42:05.456Z","count":0,"uniques":0},{"timestamp":"2025-03-30T01:50:07.604Z","count":0,"uniques":0},{"timestamp":"2025-03-31T01:48:41.586Z","count":0,"uniques":0},{"timestamp":"2025-04-01T01:54:38.254Z","count":0,"uniques":0},{"timestamp":"2025-04-02T01:44:54.776Z","count":0,"uniques":0},{"timestamp":"2025-04-03T01:43:30.533Z","count":0,"uniques":0},{"timestamp":"2025-04-04T01:43:26.487Z","count":0,"uniques":0},{"timestamp":"2025-04-05T01:41:46.603Z","count":0,"uniques":0},{"timestamp":"2025-04-06T01:48:44.618Z","count":0,"uniques":0},{"timestamp":"2025-04-07T01:46:49.608Z","count":0,"uniques":0},{"timestamp":"2025-04-08T01:44:04.218Z","count":0,"uniques":0},{"timestamp":"2025-04-09T01:44:31.927Z","count":0,"uniques":0},{"timestamp":"2025-04-10T01:44:22.611Z","count":0,"uniques":0},{"timestamp":"2025-04-11T01:44:44.933Z","count":0,"uniques":0},{"timestamp":"2025-04-12T01:42:13.286Z","count":0,"uniques":0},{"timestamp":"2025-04-13T03:11:13.032Z","count":0,"uniques":0},{"timestamp":"2025-04-14T01:48:25.736Z","count":0,"uniques":0},{"timestamp":"2025-04-15T01:47:19.326Z","count":0,"uniques":0},{"timestamp":"2025-04-16T12:45:01.536Z","count":0,"uniques":0},{"timestamp":"2025-04-17T12:45:01.536Z","count":0,"uniques":0},{"timestamp":"2025-04-18T12:45:01.536Z","count":0,"uniques":0},{"timestamp":"2025-04-19T12:45:01.536Z","count":0,"uniques":0},{"timestamp":"2025-04-20T12:45:01.536Z","count":0,"uniques":0},{"timestamp":"2025-04-21T12:45:01.536Z","count":0,"uniques":0},{"timestamp":"2025-04-22T12:45:01.536Z","count":0,"uniques":0},{"timestamp":"2025-04-23T12:45:01.536Z","count":0,"uniques":0},{"timestamp":"2025-04-24T12:45:01.536Z","count":0,"uniques":0},{"timestamp":"2025-04-25T12:45:01.536Z","count":0,"uniques":0},{"timestamp":"2025-04-26T12:45:01.536Z","count":0,"uniques":0},{"timestamp":"2025-04-27T12:45:01.536Z","count":0,"uniques":0},{"timestamp":"2025-04-28T12:45:01.536Z","count":0,"uniques":0},{"timestamp":"2025-04-29T12:45:01.536Z","count":0,"uniques":0},{"timestamp":"2025-04-30T12:45:01.536Z","count":0,"uniques":0},{"timestamp":"2025-05-01T12:45:01.536Z","count":0,"uniques":0},{"timestamp":"2025-05-02T12:45:01.536Z","count":0,"uniques":0},{"timestamp":"2025-05-03T12:45:01.536Z","count":0,"uniques":0},{"timestamp":"2025-05-04T12:45:01.536Z","count":0,"uniques":0},{"timestamp":"2025-05-05T12:45:01.536Z","count":0,"uniques":0},{"timestamp":"2025-05-06T01:49:14.976Z","count":0,"uniques":0},{"timestamp":"2025-05-07T01:50:03.429Z","count":0,"uniques":0},{"timestamp":"2025-05-08T01:50:16.313Z","count":0,"uniques":0},{"timestamp":"2025-05-09T01:49:34.987Z","count":0,"uniques":0},{"timestamp":"2025-05-10T01:45:16.360Z","count":0,"uniques":0},{"timestamp":"2025-05-11T01:55:34.343Z","count":0,"uniques":0},{"timestamp":"2025-05-12T01:54:10.287Z","count":0,"uniques":0},{"timestamp":"2025-05-13T01:51:07.455Z","count":0,"uniques":0},{"timestamp":"2025-05-14T01:50:08.729Z","count":0,"uniques":0},{"timestamp":"2025-05-15T01:48:09.507Z","count":0,"uniques":0},{"timestamp":"2025-05-16T01:51:25.957Z","count":0,"uniques":0},{"timestamp":"2025-05-17T01:47:50.078Z","count":0,"uniques":0},{"timestamp":"2025-05-18T01:56:47.843Z","count":0,"uniques":0},{"timestamp":"2025-05-19T01:55:48.274Z","count":0,"uniques":0},{"timestamp":"2025-05-20T01:52:15.030Z","count":0,"uniques":0},{"timestamp":"2025-05-21T01:51:22.241Z","count":0,"uniques":0},{"timestamp":"2025-05-22T01:50:34.030Z","count":0,"uniques":0},{"timestamp":"2025-05-23T01:50:47.506Z","count":0,"uniques":0},{"timestamp":"2025-05-24T01:46:46.580Z","count":0,"uniques":0},{"timestamp":"2025-05-25T01:59:19.818Z","count":0,"uniques":0},{"timestamp":"2025-05-26T01:54:39.670Z","count":0,"uniques":0},{"timestamp":"2025-05-27T01:50:08.810Z","count":0,"uniques":0},{"timestamp":"2025-05-28T01:52:09.010Z","count":0,"uniques":0},{"timestamp":"2025-05-29T01:51:42.415Z","count":0,"uniques":0},{"timestamp":"2025-05-30T01:49:15.550Z","count":0,"uniques":0},{"timestamp":"2025-05-31T01:49:16.044Z","count":0,"uniques":0}]
